regpy/__init__.py
regpy/_version.py
regpy/stoprules.py
regpy/functionals/__init__.py
regpy/functionals/base.py
regpy/functionals/ngsolve.py
regpy/functionals/numpy.py
regpy/hilbert/__init__.py
regpy/hilbert/base.py
regpy/hilbert/ngsolve.py
regpy/hilbert/numpy.py
regpy/operators/__init__.py
regpy/operators/base.py
regpy/operators/bases_transform.py
regpy/operators/convolution.py
regpy/operators/graph_operator.py
regpy/operators/ngsolve.py
regpy/operators/numpy.py
regpy/operators/parallel_operators.py
regpy/solvers/__init__.py
regpy/solvers/general.py
regpy/solvers/linear/__init__.py
regpy/solvers/linear/admm.py
regpy/solvers/linear/cgne.py
regpy/solvers/linear/landweber.py
regpy/solvers/linear/primal_dual.py
regpy/solvers/linear/proximal_gradient.py
regpy/solvers/linear/richardson_lucy.py
regpy/solvers/linear/semismoothNewton.py
regpy/solvers/linear/tikhonov.py
regpy/solvers/nonlinear/__init__.py
regpy/solvers/nonlinear/fista.py
regpy/solvers/nonlinear/forward_backward_splitting.py
regpy/solvers/nonlinear/gen_tikhonov.py
regpy/solvers/nonlinear/irgnm.py
regpy/solvers/nonlinear/irgnm_semismooth.py
regpy/solvers/nonlinear/landweber.py
regpy/solvers/nonlinear/newton.py
regpy/util/__init__.py
regpy/util/functional_tests.py
regpy/util/general.py
regpy/util/operator_tests.py
regpy/vecsps/__init__.py
regpy/vecsps/base.py
regpy/vecsps/curve.py
regpy/vecsps/ngsolve.py
regpy/vecsps/numpy.py
regpy-1.1.0.dist-info/licenses/LICENSE
regpy-1.1.0.dist-info/METADATA
regpy-1.1.0.dist-info/WHEEL
regpy-1.1.0.dist-info/top_level.txt
regpy-1.1.0.dist-info/RECORD
