Metadata-Version: 2.4
Name: regpy
Version: 1.1.0
Summary: A python library to solve Inverse and Ill-Posed problems by regularization
Author-email: Thorsten Hohage <hohage@math.uni-goettingen.de>
Project-URL: Homepage, https://num.math.uni-goettingen.de/regpy/
Project-URL: github, https://github.com/regpy/regpy
Keywords: inverse problems,ill-posed problems,regularization,numerical optimization,numerical analysis
Classifier: Programming Language :: Python :: 3
Classifier: License :: OSI Approved :: GNU Lesser General Public License v3 (LGPLv3)
Classifier: Operating System :: OS Independent
Requires-Python: >=3.10
License-File: LICENSE
Requires-Dist: numpy<3.0,>=2.2
Requires-Dist: scipy<2.0,>=1.12
Requires-Dist: pooch<2.0,>=1.8
Requires-Dist: pytest<9.0,>=8.0
Provides-Extra: ngsolve
Requires-Dist: ngsolve<=6.2.2501,>=6.2.2404.post2; extra == "ngsolve"
Requires-Dist: mkl!=2025.0.*,>=2023.0.0; extra == "ngsolve"
Dynamic: license-file
